{
	"name": "DelimitedText1",
	"properties": {
		"linkedServiceName": {
			"referenceName": "ragulblobstorageacc2",
			"type": "LinkedServiceReference"
		},
		"annotations": [],
		"type": "DelimitedText",
		"typeProperties": {
			"location": {
				"type": "AzureBlobStorageLocation",
				"fileName": "Purchase.csv",
				"folderPath": "ragulcopy",
				"container": "ragulsample"
			},
			"columnDelimiter": ",",
			"escapeChar": "\\",
			"firstRowAsHeader": true,
			"quoteChar": "\""
		},
		"schema": [
			{
				"name": "PO",
				"type": "String"
			},
			{
				"name": "Vender",
				"type": "String"
			},
			{
				"name": "Apple",
				"type": "String"
			},
			{
				"name": "Orange",
				"type": "String"
			}
		]
	}
}